iscraper/__init__.py
iscraper/__main__.py
iscraper/get_iplayer.py
iscraper/search.py
iscraper-0.5.dist-info/DESCRIPTION.rst
iscraper-0.5.dist-info/METADATA
iscraper-0.5.dist-info/RECORD
iscraper-0.5.dist-info/WHEEL
iscraper-0.5.dist-info/metadata.json
iscraper-0.5.dist-info/top_level.txt
