Metadata-Version: 2.0
Name: iscraper
Version: 0.5
Summary: Front end for get-iplayer to allow download by name.
Home-page: https://github.com/oldironhorse/iscraper
Author: Simon Redding
Author-email: s1m0n.r3dd1ng@gmail.com
License: GPL 3.0
Download-URL: https://github.com/oldironhorse/iscraper/archive/0.5.tar.gz
Platform: UNKNOWN
Requires-Dist: bs4
